ivr
