Metadata-Version: 1.1
Name: ivr
Version: 0.0.8
Summary: AGI Controlled IVR for Asterisk
Home-page: https://github.com/invitecomm/asterisk-ivr
Author: Brian LaVallee
Author-email: brian.lavallee@invite-comm.jp
License: GNU General Public License
Download-URL: https://github.com/invitecomm/asterisk-ivr/tarball/0.0.8
Keywords: python asterisk agi ivr telephony telephony sip voip
Platform: UNKNOWN
Classifier: Development Status :: 2 - Pre-Alpha
